alibaba_sms.py
alibaba_sms-0.0.1.dist-info/LICENSE
alibaba_sms-0.0.1.dist-info/METADATA
alibaba_sms-0.0.1.dist-info/WHEEL
alibaba_sms-0.0.1.dist-info/top_level.txt
alibaba_sms-0.0.1.dist-info/RECORD
