Metadata-Version: 2.1
Name: alibaba-sms
Version: 0.0.1
Summary: Alibaba cloud SMS service SDK
Author-email: Lin Zhiwen <zhiwenlin1116@gmail.com>
License: MIT
Project-URL: homepage, https://github.com/jayvynl/alibaba-sms
Keywords: ali,alibaba,cloud,sms,sdk
Classifier: Intended Audience :: Developers
Classifier: License :: OSI Approved :: MIT License
Classifier: Programming Language :: Python
Classifier: Programming Language :: Python :: 3
Classifier: Programming Language :: Python :: 3 :: Only
Classifier: Programming Language :: Python :: 3.6
Classifier: Programming Language :: Python :: 3.7
Classifier: Programming Language :: Python :: 3.8
Classifier: Programming Language :: Python :: 3.9
Classifier: Programming Language :: Python :: 3.10
Classifier: Programming Language :: Python :: 3.11
Requires-Python: >=3.6
License-File: LICENSE
Requires-Dist: requests
